LICENSE
badge/cov-badge.svg
fppy/__init__.py
fppy/abstract_algebra/__init__.py
fppy/abstract_algebra/abstract_algebra.py
fppy/abstract_algebra/category_algebra.py
fppy/base.py
fppy/cake.py
fppy/combinator.py
fppy/cons_list.py
fppy/cons_list_base.py
fppy/const.py
fppy/either.py
fppy/errors.py
fppy/functor.py
fppy/gt.py
fppy/lazy_evaluate.py
fppy/lazy_list.py
fppy/lazy_list_base.py
fppy/lazy_list_lambda.py
fppy/lens.py
fppy/option.py
fppy/partial_function.py
fppy/property_based_testing_tools.py
fppy/random.py
fppy/random_monad.py
fppy/try_monad.py
fppy_learn-0.3.1.dist-info/entry_points.txt
fppy_learn-0.3.1.dist-info/METADATA
fppy_learn-0.3.1.dist-info/LICENSE
fppy_learn-0.3.1.dist-info/WHEEL
fppy_learn-0.3.1.dist-info/RECORD
