Metadata-Version: 2.1
Name: fppy-learn
Version: 0.3.1
Summary: A implements of Functional Programming in Python.
Home-page: https://github.com/threecifanggen/python-functional-programming
License: MIT
Keywords: functional_programming,lambda
Author: huangbaochen
Author-email: huangbaochenwo@live.com
Requires-Python: >=3.10,<4.0
Classifier: License :: OSI Approved :: MIT License
Classifier: Operating System :: OS Independent
Classifier: Programming Language :: Python :: 3
Classifier: Programming Language :: Python :: 3.10
Classifier: Programming Language :: Python :: 3.11
Classifier: Programming Language :: Python :: 3
Requires-Dist: drill (>=1.2.0,<2.0.0)
Requires-Dist: pathos (>=0.2.8,<0.3.0)
Project-URL: Repository, https://github.com/threecifanggen/python-functional-programming
